oracle/__init__.py
oracle/cli.py
oracle/controller.py
oracle/display.py
oracle/model/__init__.py
oracle/model/choice.py
oracle/model/group.py
oracle_sh-0.3.1.dist-info/LICENSE
oracle_sh-0.3.1.dist-info/METADATA
oracle_sh-0.3.1.dist-info/WHEEL
oracle_sh-0.3.1.dist-info/entry_points.txt
oracle_sh-0.3.1.dist-info/top_level.txt
oracle_sh-0.3.1.dist-info/RECORD
